better_template_matching/LICENSE
better_template_matching/README.MD
better_template_matching/__init__.py
better_template_matching/canvas.min.js
better_template_matching/filesaver.min.js
better_template_matching/jszip.min.js
better_template_matching/requirements.txt
better_template_matching/thirdparty.json
better_template_matching/ybat.css
better_template_matching/ybat.html
better_template_matching/ybat.js
better_template_matching-0.13.dist-info/LICENSE.rst
better_template_matching-0.13.dist-info/METADATA
better_template_matching-0.13.dist-info/WHEEL
better_template_matching-0.13.dist-info/top_level.txt
better_template_matching-0.13.dist-info/RECORD
