Metadata-Version: 2.1
Name: better-template-matching
Version: 0.13
Summary: Fast template matching with multiprocessing, supports different sizes, and filters overlapping results
Home-page: https://github.com/hansalemaos/better_template_matching
Author: Johannes Fischer
Author-email: <aulasparticularesdealemaosp@gmail.com>
License: MIT
Keywords: template,matching,windows,bot,opencv
Classifier: Development Status :: 4 - Beta
Classifier: Programming Language :: Python :: 3 :: Only
Classifier: Programming Language :: Python :: 3.9
Classifier: Topic :: Scientific/Engineering :: Visualization
Classifier: Topic :: Software Development :: Libraries :: Python Modules
License-File: LICENSE.rst
Requires-Dist: a-cv2-imshow-thread
Requires-Dist: a-pandas-ex-intersection-difference
Requires-Dist: a-pandas-ex-less-memory-more-speed
Requires-Dist: a-pandas-ex-plode-tool
Requires-Dist: flatten-everything
Requires-Dist: keyboard
Requires-Dist: kthread
Requires-Dist: numpy
Requires-Dist: opencv-python
Requires-Dist: pandas
Requires-Dist: regex
Requires-Dist: requests
Requires-Dist: ujson
Requires-Dist: windows-adb-screen-capture
